{
  "definitions": [
    {
      "title": "Video Gallery",
      "id": "videogallery",
      "plugins": {
        "xwalk": {
          "page": {
            "resourceType": "core/franklin/components/block/v1/block",
            "template": {
              "name": "videogallery",
              "model": "videogallery",
              "filter": "videogallery"
            }
          }
        }
      }
    },
 {
      "title": "Video Element",
      "id": "videoelement",
      "plugins": {
        "xwalk": {
          "page": {
            "resourceType": "core/franklin/components/block/v1/block",
            "template": {
              "name": "videoelement",
              "model": "videoelement"
            }
          }
        }
      }
    }
  ],
  "models": [
    {
      "id": "videogallery",
      "fields": [

      ]
    },
     {
      "id": "videoelement",
      "fields": [
        {
          "component": "text",
          "valueType": "string[]",
          "name": "videos",
          "label": "Videos URLs"
        }
      ]
    }

  ],
  "filters": [
    {
      "id": "videogallery",
      "components": [ "videoelement"]
    }
  ]
}